README.md
setup.cfg
setup.py
pnn/__init__.py
pnn.egg-info/PKG-INFO
pnn.egg-info/SOURCES.txt
pnn.egg-info/dependency_links.txt
pnn.egg-info/requires.txt
pnn.egg-info/top_level.txt
pnn/methods/__init__.py
pnn/methods/clements.py
pnn/methods/reck.py
pnn/methods/yinyi.py
pnn/utils/__init__.py
pnn/utils/metric.py
pnn/utils/misc.py
pnn/utils/trigon.py
pnn/utils/ublock.py