Metadata-Version: 2.1
Name: pnn
Version: 0.0.5
Summary: Libraries for Photonic Neural Networks
Home-page: https://github.com/LIU-Yinyi/Photonic-Neural-Networks
Author: Yinyi
Author-email: support@liuyinyi.com
License: MIT
Download-URL: https://github.com/LIU-Yinyi/Photonic-Neural-Networks/archive/refs/tags/v0.1.0-alpha.tar.gz
Keywords: optic,photonic,neural networks,decomposition
Platform: UNKNOWN
Classifier: Development Status :: 3 - Alpha
Classifier: Intended Audience :: Developers
Classifier: Topic :: Software Development :: Build Tools
Classifier: License :: OSI Approved :: MIT License
Classifier: Programming Language :: Python :: 3
Classifier: Programming Language :: Python :: 3.5
Classifier: Programming Language :: Python :: 3.6
Classifier: Programming Language :: Python :: 3.7
Classifier: Programming Language :: Python :: 3.8
Classifier: Programming Language :: Python :: 3.9
